{"x":0,"type":"Scene","props":{"width":2000,"sceneColor":"#000000","height":0},"label":"Scene","compId":1,"child":[{"x":15,"type":"Lines","props":{"y":0,"x":0,"points":"0,0,1000,0","name":"Road","lineWidth":1,"lineColor":"#ff0000"},"label":"Road","compId":801,"child":[]},{"x":15,"type":"Image","props":{"y":-45,"x":800,"skin":"images/edit/enm01.png","scaleY":1,"scaleX":1,"name":"BlackBird//黑鸟//ID:10000","anchorY":0.5,"anchorX":0.5},"label":"BlackBird//黑鸟//ID:10000","compId":802,"child":[]},{"x":15,"type":"Image","props":{"y":-45,"x":930,"skin":"images/edit/enm01.png","scaleY":1,"scaleX":1,"name":"BlackBird//黑鸟//ID:10000","anchorY":0.5,"anchorX":0.5},"label":"BlackBird//黑鸟//ID:10000","compId":803,"child":[]},{"x":15,"type":"Lines","props":{"y":0,"x":1400,"points":"0,0,600,0","name":"Road","lineWidth":1,"lineColor":"#ff0000"},"label":"Road","compId":804,"child":[]},{"x":15,"type":"Sprite","props":{"y":0,"x":0,"name":"Chain//链"},"label":"Chain//链","compId":812,"child":[{"type":"Image","props":{"y":-150,"x":234,"skin":"images/itm_swe04_1.png","scaleY":1,"scaleX":1,"name":"EatableItem//立即生效物品//经验//ID:2030","anchorY":0.5,"anchorX":0.5},"label":"EatableItem//立即生效物品//经验//ID:2030","compId":820,"child":[]},{"type":"Image","props":{"y":-150,"x":435,"skin":"images/itm_swe04_2.png","scaleY":1,"scaleX":1,"name":"EatableItem//立即生效物品//经验//ID:2031","anchorY":0.5,"anchorX":0.5},"label":"EatableItem//立即生效物品//经验//ID:2031","compId":821,"child":[]},{"type":"Image","props":{"y":-150,"x":305,"skin":"images/logo.png","scaleY":1,"scaleX":1,"name":"EatableItem//立即生效物品//经验//ID:2000","anchorY":0.5,"anchorX":0.5},"label":"EatableItem//立即生效物品//经验//ID:2000","compId":822,"child":[]},{"type":"Image","props":{"y":-150,"x":365,"skin":"images/logo.png","scaleY":1,"scaleX":1,"name":"EatableItem//立即生效物品//经验//ID:2000","anchorY":0.5,"anchorX":0.5},"label":"EatableItem//立即生效物品//经验//ID:2000","compId":823,"child":[]}]},{"x":15,"type":"Sprite","props":{"y":0,"x":0,"name":"Chain//链"},"label":"Chain//链","compId":819,"child":[{"x":30,"type":"Image","props":{"y":-285,"x":1300,"width":75,"skin":"images/medal-2.png","scaleY":1,"scaleX":1,"rotation":0,"name":"EatableItem//立即生效物品//金币//ID:55555","height":77,"anchorY":0.5,"anchorX":0.5},"label":"EatableItem//立即生效物品//金币//ID:55555","compId":824,"child":[]},{"x":30,"type":"Image","props":{"y":-285,"x":1230,"skin":"images/medal.png","scaleY":1,"scaleX":1,"name":"EatableItem//立即生效物品//金币//ID:0","anchorY":0.5,"anchorX":0.5},"label":"EatableItem//立即生效物品//金币//ID:0","compId":825,"child":[]},{"x":30,"type":"Image","props":{"y":-285,"x":1370,"skin":"images/medal.png","scaleY":1,"scaleX":1,"name":"EatableItem//立即生效物品//金币//ID:0","anchorY":0.5,"anchorX":0.5},"label":"EatableItem//立即生效物品//金币//ID:0","compId":826,"child":[]}]}],"animations":[{"nodes":[],"name":"Road","frameRate":24,"action":0}]}